eradication_data_requirements/__init__.py
eradication_data_requirements/api.py
eradication_data_requirements/calculate_eradication_progress.py
eradication_data_requirements/calculate_intersect.py
eradication_data_requirements/cli.py
eradication_data_requirements/data_requirements_plot.py
eradication_data_requirements/fit_ramsey_time_series.py
eradication_data_requirements/mix_distributions.py
eradication_data_requirements/plot_cpue_series.py
eradication_data_requirements/plot_progress_probability.py
eradication_data_requirements/progress_probability.py
eradication_data_requirements/resample_aerial_monitoring.py
eradication_data_requirements/resample_raw_data.py
eradication_data_requirements/set_data.py
eradication_data_requirements-7.0.0.dist-info/licenses/LICENSE
eradication_data_requirements-7.0.0.dist-info/WHEEL
eradication_data_requirements-7.0.0.dist-info/METADATA
eradication_data_requirements-7.0.0.dist-info/RECORD
