Metadata-Version: 2.4
Name: eradication_data_requirements
Version: 7.0.0
Summary: A template Python module
Home-page: https://github.com/IslasGECI/eradication_data_requirements
Author: Ciencia de Datos • GECI
Author-email: ciencia.datos@islas.org.mx
Requires-Python: >=3.9
Classifier: License :: OSI Approved :: GNU General Public License v3 or later (GPLv3+)
License-File: LICENSE
Requires-Dist: bootstrapping-tools==3.*
Requires-Dist: fastapi
Requires-Dist: geci-plots==0.4.*
Requires-Dist: httpx
Requires-Dist: numpy
Requires-Dist: pandas
Requires-Dist: python-multipart
Requires-Dist: typer[all]
